{
  "workers": [
    {
      "name": "Luiz",
      "contact": "(34)33333-1524",
      "category": "Eletrica",
      "abstract": "Não gostei, não finalizou o serviço",
      "id": 24
    },
    {
      "name": "Kátia",
      "contact": "(34)33333-1524",
      "category": "Construcao",
      "abstract": "Adorei, muito pontual!",
      "id": 25
    },
    {
      "name": "Felipe",
      "contact": "(34)33333-1524",
      "category": "Construcao",
      "abstract": "Acabamento Top",
      "id": 26
    },
    {
      "name": "Maurício",
      "contact": "(34)33333-1524",
      "category": "Hidraulica",
      "abstract": "Fez a troca de algumas saídas de água, gostei",
      "id": 27
    },
    {
      "name": "Osvaldo",
      "contact": "(34)33333-1524",
      "category": "Limpeza",
      "abstract": "A casa ficou um brinco e deixou tudo organizado, limpou os vidros e varanda direitinho, amei muito!!",
      "id": 28
    },
    {
      "name": "Celso",
      "contact": "(34)99104-4444",
      "category": "Eletrica",
      "abstract": "Muito bom ",
      "id": 29
    },
    {
      "name": "Carla",
      "contact": "(34)99104-4444",
      "category": "Eletrica",
      "abstract": "Gostei",
      "id": 30
    },
    {
      "name": "Fábio",
      "contact": "(34)92224-6988",
      "category": "Construcao",
      "abstract": "Não gostei",
      "id": 31
    },
    {
      "name": "Miguel",
      "contact": "(34)21533-6658",
      "category": "Construcao",
      "abstract": "Adorei",
      "id": 32
    },
    {
      "name": "Keila",
      "contact": "(35)44444-2552",
      "category": "Construcao",
      "abstract": "Não gostei",
      "id": 33
    },
    {
      "name": "Marcela",
      "contact": "(12)55245-5552",
      "category": "Eletrica",
      "abstract": "Adorei o serviço dela",
      "id": 34
    },
    {
      "name": "Italo",
      "contact": "(25)55555-4555",
      "category": "Construcao",
      "abstract": "Gostei",
      "id": 35
    },
    {
      "name": "teste",
      "contact": "(22)22222-2222",
      "category": "Construcao",
      "abstract": "teste",
      "id": 36
    },
    {
      "name": "Teste",
      "contact": "(33)33333-3333",
      "category": "Construcao",
      "abstract": "Teste",
      "id": 37
    },
    {
      "name": "Carla",
      "contact": "(33)33333-3333",
      "category": "Eletrica",
      "abstract": "Teste",
      "id": 38
    },
    {
      "name": "New",
      "contact": "(22)22222-2222",
      "category": "Construcao",
      "abstract": "wwwww",
      "id": 39
    },
    {
      "name": "New",
      "contact": "(55)55555-5522",
      "category": "Eletrica",
      "abstract": "jhuhuhu",
      "id": 40
    },
    {
      "name": "jdhajs",
      "contact": "(55)55555-5555",
      "category": "Construcao",
      "abstract": "ssss",
      "id": 41
    },
    {
      "name": "wqsqw",
      "contact": "(33)33333-3333",
      "category": "Construcao",
      "abstract": "wwwwwwwwwwwwwwwwwwwwwww",
      "id": 42
    },
    {
      "name": "New",
      "contact": "(33)33333-3333",
      "category": "Eletrica",
      "abstract": "3333333333",
      "id": 43
    }
  ]
}